safeway/__init__.py
safeway/safeway.py
safeway/unit_homogenizer.py
python_safeway-0.0.1.dist-info/LICENSE
python_safeway-0.0.1.dist-info/METADATA
python_safeway-0.0.1.dist-info/WHEEL
python_safeway-0.0.1.dist-info/top_level.txt
python_safeway-0.0.1.dist-info/RECORD
